LICENSE
MANIFEST.in
README.md
pyproject.toml
setup.cfg
setup.py
docassemble.LAWVRetainer.egg-info/PKG-INFO
docassemble.LAWVRetainer.egg-info/SOURCES.txt
docassemble.LAWVRetainer.egg-info/dependency_links.txt
docassemble.LAWVRetainer.egg-info/not-zip-safe
docassemble.LAWVRetainer.egg-info/top_level.txt
docassemble/LAWVRetainer/__init__.py
docassemble/LAWVRetainer/data/questions/retainer.yml
docassemble/LAWVRetainer/data/sources/README.md
docassemble/LAWVRetainer/data/static/README.md
docassemble/LAWVRetainer/data/static/bha_sample.pdf
docassemble/LAWVRetainer/data/static/fast_sample.pdf
docassemble/LAWVRetainer/data/static/lawv_retainer_sample.pdf
docassemble/LAWVRetainer/data/static/lawv_retainer_spanish_sample.pdf
docassemble/LAWVRetainer/data/static/non_citizen_status_worksheet.pdf
docassemble/LAWVRetainer/data/static/non_citizen_status_worksheet.png
docassemble/LAWVRetainer/data/templates/README.md
docassemble/LAWVRetainer/data/templates/bha.pdf
docassemble/LAWVRetainer/data/templates/fast.pdf
docassemble/LAWVRetainer/data/templates/lawv_retainer.pdf
docassemble/LAWVRetainer/data/templates/lawv_retainer_spanish.pdf