Metadata-Version: 2.4
Name: docassemble.LAWVRetainer
Version: 2.0.0
Summary: A docassemble extension to utilizing a multi-part interview to create either a 1) Legal, 2) Spanish, 3) FAST, or 4) BHA retainer
Home-page: https://docassemble.org
Author: Dane Henry, Esq.
Author-email: dhenry@lawv.net
License: The MIT License (MIT)
License-File: LICENSE
Dynamic: author
Dynamic: author-email
Dynamic: description
Dynamic: description-content-type
Dynamic: home-page
Dynamic: license
Dynamic: license-file
Dynamic: summary
